package/__init__.py
package/main.py
Instalpypi-1.0.0.dist-info/LICENSE
Instalpypi-1.0.0.dist-info/METADATA
Instalpypi-1.0.0.dist-info/WHEEL
Instalpypi-1.0.0.dist-info/top_level.txt
Instalpypi-1.0.0.dist-info/RECORD
